Metadata-Version: 1.0
Name: myaws
Version: 0.0.1
Summary: Python AWS CLI Tool
Home-page: https://github.com/yhidetoshi/python-awscli-tool
Author: yhidetoshi
Author-email: example@python.net
License: MIT
Platform: UNKNOWN
